{"cameraMode":{"drawMode":0,"name":"Shaded","section":"Shading Mode"},"sceneLighting":false,"audioPlay":false,"sceneViewState":{"m_AlwaysRefresh":false,"showFog":true,"showSkybox":false,"showFlares":true,"showImageEffects":true,"showParticleSystems":true,"showVisualEffectGraphs":true,"m_FxEnabled":true},"in2DMode":false,"pivot":{"x":-64.99993896484375,"y":-25.0,"z":0.0},"rotation":{"x":0.09226623922586441,"y":0.004481006879359484,"z":-0.0004140061209909618,"w":0.9957298040390015},"size":584.5983276367188,"orthographic":false}